{"ref": "Penei Yehoshua on Kiddushin 1", "heRef": "פני יהושע על קידושין א׳", "isComplex": false, "text": [], "he": [], "spanning": true, "versions": [], "textDepth": 2, "sectionNames": ["Daf", "Comment"], "addressTypes": ["Talmud", "Integer"], "lengths": [164, 1212], "length": 164, "heTitle": "פני יהושע על קידושין א׳", "titleVariants": ["Penei Yehoshua on Kiddushin"], "heTitleVariants": ["פני יהושע על קידושין"], "type": "Commentary", "primary_category": "Commentary", "book": "Penei Yehoshua on Kiddushin", "categories": ["Talmud", "Bavli", "Acharonim on Talmud", "Penei Yehoshua"], "order": "", "sections": ["1a"], "toSections": ["1b"], "commentator": "Penei Yehoshua", "heCommentator": "פני יהושע", "collectiveTitle": "Penei Yehoshua", "heCollectiveTitle": "פני יהושע", "baseTexTitles": ["Kiddushin"], "isDependant": true, "indexTitle": "Penei Yehoshua on Kiddushin", "heIndexTitle": "פני יהושע על קידושין", "sectionRef": "Penei Yehoshua on Kiddushin 1", "firstAvailableSectionRef": "Penei Yehoshua on Kiddushin 2a", "heSectionRef": "פני יהושע על קידושין א׳", "isSpanning": true, "spanningRefs": ["Penei Yehoshua on Kiddushin 1a", "Penei Yehoshua on Kiddushin 1b"], "title": "Penei Yehoshua on Kiddushin 1", "heBook": "פני יהושע על קידושין", "alts": [], "index_offsets_by_depth": {}, "next": "Penei Yehoshua on Kiddushin 2a", "prev": null, "commentary": [], "sheets": [], "layer": []}