{"ref": "Ben Yehoyada on Gittin 1", "heRef": "בן יהוידע על גיטין א׳", "isComplex": false, "text": [], "he": [], "spanning": true, "versions": [], "textDepth": 2, "sectionNames": ["Daf", "Paragraph"], "addressTypes": ["Talmud", "Integer"], "lengths": [180, 148], "length": 180, "heTitle": "בן יהוידע על גיטין א׳", "titleVariants": ["Ben Yehoyada on Gittin"], "heTitleVariants": ["בן יהוידע על גיטין"], "type": "Commentary", "primary_category": "Commentary", "book": "Ben Yehoyada on Gittin", "categories": ["Talmud", "Bavli", "Acharonim on Talmud", "Ben Yehoyada"], "order": "", "sections": ["1a"], "toSections": ["1b"], "commentator": "Ben Yehoyada", "heCommentator": "בן יהוידע", "collectiveTitle": "Ben Yehoyada", "heCollectiveTitle": "בן יהוידע", "baseTexTitles": ["Gittin"], "isDependant": true, "indexTitle": "Ben Yehoyada on Gittin", "heIndexTitle": "בן יהוידע על גיטין", "sectionRef": "Ben Yehoyada on Gittin 1", "firstAvailableSectionRef": "Ben Yehoyada on Gittin 6a", "heSectionRef": "בן יהוידע על גיטין א׳", "isSpanning": true, "spanningRefs": ["Ben Yehoyada on Gittin 1a", "Ben Yehoyada on Gittin 1b"], "title": "Ben Yehoyada on Gittin 1", "heBook": "בן יהוידע על גיטין", "alts": [], "index_offsets_by_depth": {}, "next": "Ben Yehoyada on Gittin 6a", "prev": null, "commentary": [], "sheets": [], "layer": []}